sdram_controller.v
`timescale 1ns / 1ps

module sdram_controller #(
    parameter CLK_FREQ_MHZ   = 1,
    parameter CAS_LATENCY    = 2,
    parameter T_RC           = 9,
    parameter T_RCD          = 2,
    parameter T_RP           = 2,
    parameter T_WR           = 2,
    parameter T_MRD          = 2,
    parameter REFRESH_CYCLES = 750,
    parameter SDRAM_DATA_WIDTH = 16,
    parameter SDRAM_ADDR_WIDTH = 13,
    parameter SDRAM_COL_WIDTH  = 9,
    parameter SDRAM_ROW_WIDTH  = 13,
    parameter SDRAM_BANK_WIDTH = 2,
    parameter HOST_ADDR_WIDTH  = 24
)(
    input  wire                        clk,
    input  wire                        rst_n,
    input  wire                        host_req,
    input  wire                        host_we,
    input  wire [HOST_ADDR_WIDTH-1:0]  host_addr,
    input  wire [SDRAM_DATA_WIDTH-1:0] host_wdata,
    input  wire [1:0]                  host_be,
    output reg                         host_ack,
    output reg                         host_rdata_valid,
    output reg  [SDRAM_DATA_WIDTH-1:0] host_rdata,
    output reg                         sdram_cke,
    output reg                         sdram_cs_n,
    output reg                         sdram_ras_n,
    output reg                         sdram_cas_n,
    output reg                         sdram_we_n,
    output reg  [SDRAM_BANK_WIDTH-1:0] sdram_ba,
    output reg  [SDRAM_ADDR_WIDTH-1:0] sdram_addr,
    inout  wire [SDRAM_DATA_WIDTH-1:0] sdram_dq,
    output reg  [1:0]                  sdram_dqm
);

    localparam CMD_NOP       = 4'b0111;
    localparam CMD_ACTIVE    = 4'b0011;
    localparam CMD_READ      = 4'b0101;
    localparam CMD_WRITE     = 4'b0100;
    localparam CMD_PRECHARGE = 4'b0010;
    localparam CMD_REFRESH   = 4'b0001;
    localparam CMD_LOAD_MODE = 4'b0000;

    localparam S_INIT_WAIT = 4'd0;
    localparam S_INIT_PRE  = 4'd1;
    localparam S_INIT_REF1 = 4'd2;
    localparam S_INIT_REF2 = 4'd3;
    localparam S_INIT_MRS  = 4'd4;
    localparam S_IDLE      = 4'd5;
    localparam S_REFRESH   = 4'd6;
    localparam S_ACTIVE    = 4'd7;
    localparam S_READ      = 4'd8;
    localparam S_WRITE     = 4'd9;

    reg [3:0]  state;
    reg [15:0] init_timer;
    reg [9:0]  refresh_timer;
    reg [3:0]  cmd_timer;
    reg        refresh_req;

    wire [SDRAM_BANK_WIDTH-1:0] req_bank = host_addr[HOST_ADDR_WIDTH-1 : HOST_ADDR_WIDTH-SDRAM_BANK_WIDTH];
    wire [SDRAM_ROW_WIDTH-1:0]  req_row  = host_addr[HOST_ADDR_WIDTH-SDRAM_BANK_WIDTH-1 : SDRAM_COL_WIDTH];
    wire [SDRAM_COL_WIDTH-1:0]  req_col  = host_addr[SDRAM_COL_WIDTH-1:0];

    reg                          dq_oe;
    reg  [SDRAM_DATA_WIDTH-1:0]  dq_out;
    assign sdram_dq = dq_oe ? dq_out : {SDRAM_DATA_WIDTH{1'bz}};

    reg  [SDRAM_DATA_WIDTH-1:0]  rd_pipe [0:3];
    reg  [3:0]                   rd_valid_pipe;
    reg  [SDRAM_DATA_WIDTH-1:0]  wr_data_lat;
    reg  [1:0]                   wr_be_lat;
    reg                          wr_pending;

    localparam INIT_WAIT_CYCLES = 200 * CLK_FREQ_MHZ;

    // Refresh timer
    always @(posedge clk or negedge rst_n) begin
        if (!rst_n) begin
            refresh_timer <= 0;
            refresh_req   <= 0;
        end else begin
            if (state == S_REFRESH)
                refresh_req <= 0;
            else if (refresh_timer == REFRESH_CYCLES - 1) begin
                refresh_timer <= 0;
                refresh_req   <= 1;
            end else
                refresh_timer <= refresh_timer + 1;
        end
    end

    // Init timer
    always @(posedge clk or negedge rst_n) begin
        if (!rst_n)
            init_timer <= INIT_WAIT_CYCLES[15:0];
        else if (init_timer != 0)
            init_timer <= init_timer - 1;
    end

    // Command timer
    always @(posedge clk or negedge rst_n) begin
        if (!rst_n)
            cmd_timer <= 0;
        else if (cmd_timer != 0)
            cmd_timer <= cmd_timer - 1;
    end

    // Main FSM
    always @(posedge clk or negedge rst_n) begin
        if (!rst_n) begin
            state            <= S_INIT_WAIT;
            host_ack         <= 0;
            host_rdata_valid <= 0;
            dq_oe            <= 0;
            sdram_cke        <= 1;
            sdram_cs_n       <= 1;
            sdram_ras_n      <= 1;
            sdram_cas_n      <= 1;
            sdram_we_n       <= 1;
            sdram_ba         <= 0;
            sdram_addr       <= 0;
            sdram_dqm        <= 2'b11;
            rd_valid_pipe    <= 0;
            wr_pending       <= 0;
        end else begin

            // Defaults every cycle
            sdram_cs_n  <= 0;
            sdram_ras_n <= 1;
            sdram_cas_n <= 1;
            sdram_we_n  <= 1;
            host_ack    <= 0;
            dq_oe       <= 0;

            // Shift read pipeline
            rd_valid_pipe <= {rd_valid_pipe[2:0], 1'b0};
            rd_pipe[0]    <= sdram_dq;
            rd_pipe[1]    <= rd_pipe[0];
            rd_pipe[2]    <= rd_pipe[1];
            rd_pipe[3]    <= rd_pipe[2];

            // Read data output
            if (rd_valid_pipe[CAS_LATENCY]) begin
                host_rdata       <= rd_pipe[CAS_LATENCY-1];
                host_rdata_valid <= 1;
            end else
                host_rdata_valid <= 0;

            case (state)

                S_INIT_WAIT: begin
                    sdram_cs_n <= 1;
                    sdram_dqm  <= 2'b11;
                    if (init_timer == 0) begin
                        state       <= S_INIT_PRE;
                        sdram_cs_n  <= 0;
                        sdram_ras_n <= 0;
                        sdram_we_n  <= 0;
                        sdram_addr  <= 13'b0010000000000;
                        cmd_timer   <= T_RP;
                    end
                end

                S_INIT_PRE: begin
                    if (cmd_timer == 0) begin
                        state       <= S_INIT_REF1;
                        sdram_ras_n <= 0;
                        sdram_cas_n <= 0;
                        cmd_timer   <= T_RC;
                    end
                end

                S_INIT_REF1: begin
                    if (cmd_timer == 0) begin
                        state       <= S_INIT_REF2;
                        sdram_ras_n <= 0;
                        sdram_cas_n <= 0;
                        cmd_timer   <= T_RC;
                    end
                end

                S_INIT_REF2: begin
                    if (cmd_timer == 0) begin
                        state       <= S_INIT_MRS;
                        sdram_ras_n <= 0;
                        sdram_cas_n <= 0;
                        sdram_we_n  <= 0;
                        sdram_addr  <= 13'b0000000100000;
                        sdram_ba    <= 0;
                        cmd_timer   <= T_MRD;
                    end
                end

                S_INIT_MRS: begin
                    if (cmd_timer == 0)
                        state <= S_IDLE;
                end

                S_IDLE: begin
                    sdram_dqm <= 2'b11;
                    if (refresh_req) begin
                        state       <= S_REFRESH;
                        sdram_ras_n <= 0;
                        sdram_cas_n <= 0;
                        cmd_timer   <= T_RC;
                    end else if (host_req) begin
                        // Latch request
                        wr_data_lat <= host_wdata;
                        wr_be_lat   <= host_be;
                        wr_pending  <= host_we;
                        host_ack    <= 1;
                        // Issue ACTIVE
                        state       <= S_ACTIVE;
                        sdram_ras_n <= 0;
                        sdram_ba    <= req_bank;
                        sdram_addr  <= {{SDRAM_ADDR_WIDTH-SDRAM_ROW_WIDTH{1'b0}}, req_row};
                        cmd_timer   <= T_RCD;
                    end
                end

                S_REFRESH: begin
                    if (cmd_timer == 0)
                        state <= S_IDLE;
                end

                S_ACTIVE: begin
                    if (cmd_timer == 0) begin
                        if (wr_pending) begin
                            state       <= S_WRITE;
                            sdram_cas_n <= 0;
                            sdram_we_n  <= 0;
                            sdram_ba    <= req_bank;
                            sdram_addr  <= {{SDRAM_ADDR_WIDTH-SDRAM_COL_WIDTH-1{1'b0}}, 1'b1, req_col};
                            dq_oe       <= 1;
                            dq_out      <= wr_data_lat;
                            sdram_dqm   <= ~wr_be_lat;
                            cmd_timer   <= T_WR + T_RP;
                        end else begin
                            state       <= S_READ;
                            sdram_cas_n <= 0;
                            sdram_ba    <= req_bank;
                            sdram_addr  <= {{SDRAM_ADDR_WIDTH-SDRAM_COL_WIDTH-1{1'b0}}, 1'b1, req_col};
                            sdram_dqm   <= 2'b00;
                            rd_valid_pipe[0] <= 1;
                            cmd_timer   <= CAS_LATENCY + 1;
                        end
                    end
                end

                S_READ: begin
                    sdram_dqm <= 2'b00;
                    if (cmd_timer == 0)
                        state <= S_IDLE;
                end

                S_WRITE: begin
                    dq_oe     <= 1;
                    dq_out    <= wr_data_lat;
                    sdram_dqm <= ~wr_be_lat;
                    if (cmd_timer == 0) begin
                        dq_oe <= 0;
                        state <= S_IDLE;
                    end
                end

                default: state <= S_IDLE;
            endcase
        end
    end

endmodule

tb_sdram_controller.v
`timescale 1ns / 1ps

module tb_sdram_controller;

    localparam CLK_PERIOD = 10;
    localparam DATA_WIDTH = 16;
    localparam ADDR_WIDTH = 24;

    reg                    clk, rst_n;
    reg                    host_req, host_we;
    reg  [ADDR_WIDTH-1:0]  host_addr;
    reg  [DATA_WIDTH-1:0]  host_wdata;
    reg  [1:0]             host_be;

    wire                   host_ack;
    wire                   host_rdata_valid;
    wire [DATA_WIDTH-1:0]  host_rdata;
    wire                   sdram_cke, sdram_cs_n, sdram_ras_n;
    wire                   sdram_cas_n, sdram_we_n;
    wire [1:0]             sdram_ba, sdram_dqm;
    wire [12:0]            sdram_addr;
    wire [DATA_WIDTH-1:0]  sdram_dq;

    // Simple SDRAM model: drive dq_model onto the bus
    reg [DATA_WIDTH-1:0] sdram_dq_model;
    assign sdram_dq = sdram_dq_model;

    sdram_controller #(
        .CLK_FREQ_MHZ   (1),
        .CAS_LATENCY    (2),
        .REFRESH_CYCLES (750)
    ) dut (
        .clk              (clk),
        .rst_n            (rst_n),
        .host_req         (host_req),
        .host_we          (host_we),
        .host_addr        (host_addr),
        .host_wdata       (host_wdata),
        .host_be          (host_be),
        .host_ack         (host_ack),
        .host_rdata_valid (host_rdata_valid),
        .host_rdata       (host_rdata),
        .sdram_cke        (sdram_cke),
        .sdram_cs_n       (sdram_cs_n),
        .sdram_ras_n      (sdram_ras_n),
        .sdram_cas_n      (sdram_cas_n),
        .sdram_we_n       (sdram_we_n),
        .sdram_ba         (sdram_ba),
        .sdram_addr       (sdram_addr),
        .sdram_dq         (sdram_dq),
        .sdram_dqm        (sdram_dqm)
    );

    // Clock
    initial clk = 0;
    always #(CLK_PERIOD/2) clk = ~clk;

    // Timeout watchdog
    initial begin
        #2000000;
        $display("TIMEOUT - simulation exceeded time limit");
        $finish;
    end

    initial begin
        $dumpfile("sdram_tb.vcd");
        $dumpvars(0, tb_sdram_controller);

        // Initialise inputs
        sdram_dq_model = 16'hZZZZ;
        rst_n          = 0;
        host_req       = 0;
        host_we        = 0;
        host_addr      = 0;
        host_wdata     = 0;
        host_be        = 2'b11;

        // Hold reset for 5 cycles
        repeat(5) @(posedge clk);
        rst_n = 1;
        $display("[%0t] Reset released", $time);

        // Wait until FSM is in S_IDLE (state = 5)
        wait (dut.state === 4'd5);
        @(posedge clk);
        $display("[%0t] FSM is IDLE - ready for transactions", $time);

        //--------------------------------------------------
        // WRITE: hold host_req HIGH until ack comes back
        //--------------------------------------------------
        $display("[%0t] Starting WRITE", $time);
        host_addr  = 24'h000100;
        host_wdata = 16'hABCD;
        host_be    = 2'b11;
        host_we    = 1;
        host_req   = 1;          // keep high until ack

        wait (host_ack === 1);   // FSM accepted the request
        @(posedge clk);
        host_req = 0;            // now safe to deassert
        $display("[%0t] Write ACK received", $time);

        // Wait for FSM to return to IDLE
        wait (dut.state === 4'd5);
        repeat(3) @(posedge clk);

        //--------------------------------------------------
        // READ: same pattern - hold req until ack
        //--------------------------------------------------
        $display("[%0t] Starting READ", $time);
        sdram_dq_model = 16'hABCD;   // SDRAM drives this data back
        host_addr = 24'h000100;
        host_we   = 0;
        host_req  = 1;               // keep high until ack

        wait (host_ack === 1);
        @(posedge clk);
        host_req = 0;
        $display("[%0t] Read ACK received", $time);

        // Wait for read data to come back through pipeline
        wait (host_rdata_valid === 1);
        $display("[%0t] Read data = 0x%04X  (expected 0xABCD)", $time, host_rdata);

        if (host_rdata === 16'hABCD)
            $display("PASS: data matches");
        else
            $display("FAIL: got 0x%04X", host_rdata);

        repeat(10) @(posedge clk);
        $display("Simulation complete.");
        $finish;
    end

endmodule

sdram_tb.vcd
$date
	Thu Apr 16 21:56:32 2026
$end
$version
	Icarus Verilog
$end
$timescale
	1ps
$end
$scope module tb_sdram_controller $end
$var wire 16 ! sdram_dq [15:0] $end
$var wire 1 " sdram_we_n $end
$var wire 1 # sdram_ras_n $end
$var wire 2 $ sdram_dqm [1:0] $end
$var wire 1 % sdram_cs_n $end
$var wire 1 & sdram_cke $end
$var wire 1 ' sdram_cas_n $end
$var wire 2 ( sdram_ba [1:0] $end
$var wire 13 ) sdram_addr [12:0] $end
$var wire 1 * host_rdata_valid $end
$var wire 16 + host_rdata [15:0] $end
$var wire 1 , host_ack $end
$var reg 1 - clk $end
$var reg 24 . host_addr [23:0] $end
$var reg 2 / host_be [1:0] $end
$var reg 1 0 host_req $end
$var reg 16 1 host_wdata [15:0] $end
$var reg 1 2 host_we $end
$var reg 1 3 rst_n $end
$var reg 16 4 sdram_dq_model [15:0] $end
$scope module dut $end
$var wire 1 - clk $end
$var wire 24 5 host_addr [23:0] $end
$var wire 2 6 host_be [1:0] $end
$var wire 1 0 host_req $end
$var wire 16 7 host_wdata [15:0] $end
$var wire 1 2 host_we $end
$var wire 1 3 rst_n $end
$var wire 16 8 sdram_dq [15:0] $end
$var wire 13 9 req_row [12:0] $end
$var wire 9 : req_col [8:0] $end
$var wire 2 ; req_bank [1:0] $end
$var reg 4 < cmd_timer [3:0] $end
$var reg 1 = dq_oe $end
$var reg 16 > dq_out [15:0] $end
$var reg 1 , host_ack $end
$var reg 16 ? host_rdata [15:0] $end
$var reg 1 * host_rdata_valid $end
$var reg 16 @ init_timer [15:0] $end
$var reg 4 A rd_valid_pipe [3:0] $end
$var reg 1 B refresh_req $end
$var reg 10 C refresh_timer [9:0] $end
$var reg 13 D sdram_addr [12:0] $end
$var reg 2 E sdram_ba [1:0] $end
$var reg 1 ' sdram_cas_n $end
$var reg 1 & sdram_cke $end
$var reg 1 % sdram_cs_n $end
$var reg 2 F sdram_dqm [1:0] $end
$var reg 1 # sdram_ras_n $end
$var reg 1 " sdram_we_n $end
$var reg 4 G state [3:0] $end
$var reg 2 H wr_be_lat [1:0] $end
$var reg 16 I wr_data_lat [15:0] $end
$var reg 1 J wr_pending $end
$upscope $end
$upscope $end
$enddefinitions $end
#0
$dumpvars
0J
bx I
bx H
b0 G
b11 F
b0 E
b0 D
b0 C
0B
b0 A
b11001000 @
bx ?
bx >
0=
b0 <
b0 ;
b0 :
b0 9
bz 8
b0 7
b11 6
b0 5
bz 4
03
02
b0 1
00
b11 /
b0 .
0-
0,
bx +
0*
b0 )
b0 (
1'
1&
1%
b11 $
1#
1"
bz !
$end
#5000
1-
#10000
0-
#15000
1-
#20000
0-
#25000
1-
#30000
0-
#35000
1-
#40000
0-
#45000
1%
b11000111 @
b1 C
13
1-
#50000
0-
#55000
b10 C
b11000110 @
1%
1-
#60000
0-
#65000
1%
b11000101 @
b11 C
1-
#70000
0-
#75000
b100 C
b11000100 @
1%
1-
#80000
0-
#85000
1%
b11000011 @
b101 C
1-
#90000
0-
#95000
b110 C
b11000010 @
1%
1-
#100000
0-
#105000
1%
b11000001 @
b111 C
1-
#110000
0-
#115000
b1000 C
b11000000 @
1%
1-
#120000
0-
#125000
1%
b10111111 @
b1001 C
1-
#130000
0-
#135000
b1010 C
b10111110 @
1%
1-
#140000
0-
#145000
1%
b10111101 @
b1011 C
1-
#150000
0-
#155000
b1100 C
b10111100 @
1%
1-
#160000
0-
#165000
1%
b10111011 @
b1101 C
1-
#170000
0-
#175000
b1110 C
b10111010 @
1%
1-
#180000
0-
#185000
1%
b10111001 @
b1111 C
1-
#190000
0-
#195000
b10000 C
b10111000 @
1%
1-
#200000
0-
#205000
1%
b10110111 @
b10001 C
1-
#210000
0-
#215000
b10010 C
b10110110 @
1%
1-
#220000
0-
#225000
1%
b10110101 @
b10011 C
1-
#230000
0-
#235000
b10100 C
b10110100 @
1%
1-
#240000
0-
#245000
1%
b10110011 @
b10101 C
1-
#250000
0-
#255000
b10110 C
b10110010 @
1%
1-
#260000
0-
#265000
1%
b10110001 @
b10111 C
1-
#270000
0-
#275000
b11000 C
b10110000 @
1%
1-
#280000
0-
#285000
1%
b10101111 @
b11001 C
1-
#290000
0-
#295000
b11010 C
b10101110 @
1%
1-
#300000
0-
#305000
1%
b10101101 @
b11011 C
1-
#310000
0-
#315000
b11100 C
b10101100 @
1%
1-
#320000
0-
#325000
1%
b10101011 @
b11101 C
1-
#330000
0-
#335000
b11110 C
b10101010 @
1%
1-
#340000
0-
#345000
1%
b10101001 @
b11111 C
1-
#350000
0-
#355000
b100000 C
b10101000 @
1%
1-
#360000
0-
#365000
1%
b10100111 @
b100001 C
1-
#370000
0-
#375000
b100010 C
b10100110 @
1%
1-
#380000
0-
#385000
1%
b10100101 @
b100011 C
1-
#390000
0-
#395000
b100100 C
b10100100 @
1%
1-
#400000
0-
#405000
1%
b10100011 @
b100101 C
1-
#410000
0-
#415000
b100110 C
b10100010 @
1%
1-
#420000
0-
#425000
1%
b10100001 @
b100111 C
1-
#430000
0-
#435000
b101000 C
b10100000 @
1%
1-
#440000
0-
#445000
1%
b10011111 @
b101001 C
1-
#450000
0-
#455000
b101010 C
b10011110 @
1%
1-
#460000
0-
#465000
1%
b10011101 @
b101011 C
1-
#470000
0-
#475000
b101100 C
b10011100 @
1%
1-
#480000
0-
#485000
1%
b10011011 @
b101101 C
1-
#490000
0-
#495000
b101110 C
b10011010 @
1%
1-
#500000
0-
#505000
1%
b10011001 @
b101111 C
1-
#510000
0-
#515000
b110000 C
b10011000 @
1%
1-
#520000
0-
#525000
1%
b10010111 @
b110001 C
1-
#530000
0-
#535000
b110010 C
b10010110 @
1%
1-
#540000
0-
#545000
1%
b10010101 @
b110011 C
1-
#550000
0-
#555000
b110100 C
b10010100 @
1%
1-
#560000
0-
#565000
1%
b10010011 @
b110101 C
1-
#570000
0-
#575000
b110110 C
b10010010 @
1%
1-
#580000
0-
#585000
1%
b10010001 @
b110111 C
1-
#590000
0-
#595000
b111000 C
b10010000 @
1%
1-
#600000
0-
#605000
1%
b10001111 @
b111001 C
1-
#610000
0-
#615000
b111010 C
b10001110 @
1%
1-
#620000
0-
#625000
1%
b10001101 @
b111011 C
1-
#630000
0-
#635000
b111100 C
b10001100 @
1%
1-
#640000
0-
#645000
1%
b10001011 @
b111101 C
1-
#650000
0-
#655000
b111110 C
b10001010 @
1%
1-
#660000
0-
#665000
1%
b10001001 @
b111111 C
1-
#670000
0-
#675000
b1000000 C
b10001000 @
1%
1-
#680000
0-
#685000
1%
b10000111 @
b1000001 C
1-
#690000
0-
#695000
b1000010 C
b10000110 @
1%
1-
#700000
0-
#705000
1%
b10000101 @
b1000011 C
1-
#710000
0-
#715000
b1000100 C
b10000100 @
1%
1-
#720000
0-
#725000
1%
b10000011 @
b1000101 C
1-
#730000
0-
#735000
b1000110 C
b10000010 @
1%
1-
#740000
0-
#745000
1%
b10000001 @
b1000111 C
1-
#750000
0-
#755000
b1001000 C
b10000000 @
1%
1-
#760000
0-
#765000
1%
b1111111 @
b1001001 C
1-
#770000
0-
#775000
b1001010 C
b1111110 @
1%
1-
#780000
0-
#785000
1%
b1111101 @
b1001011 C
1-
#790000
0-
#795000
b1001100 C
b1111100 @
1%
1-
#800000
0-
#805000
1%
b1111011 @
b1001101 C
1-
#810000
0-
#815000
b1001110 C
b1111010 @
1%
1-
#820000
0-
#825000
1%
b1111001 @
b1001111 C
1-
#830000
0-
#835000
b1010000 C
b1111000 @
1%
1-
#840000
0-
#845000
1%
b1110111 @
b1010001 C
1-
#850000
0-
#855000
b1010010 C
b1110110 @
1%
1-
#860000
0-
#865000
1%
b1110101 @
b1010011 C
1-
#870000
0-
#875000
b1010100 C
b1110100 @
1%
1-
#880000
0-
#885000
1%
b1110011 @
b1010101 C
1-
#890000
0-
#895000
b1010110 C
b1110010 @
1%
1-
#900000
0-
#905000
1%
b1110001 @
b1010111 C
1-
#910000
0-
#915000
b1011000 C
b1110000 @
1%
1-
#920000
0-
#925000
1%
b1101111 @
b1011001 C
1-
#930000
0-
#935000
b1011010 C
b1101110 @
1%
1-
#940000
0-
#945000
1%
b1101101 @
b1011011 C
1-
#950000
0-
#955000
b1011100 C
b1101100 @
1%
1-
#960000
0-
#965000
1%
b1101011 @
b1011101 C
1-
#970000
0-
#975000
b1011110 C
b1101010 @
1%
1-
#980000
0-
#985000
1%
b1101001 @
b1011111 C
1-
#990000
0-
#995000
b1100000 C
b1101000 @
1%
1-
#1000000
0-
#1005000
1%
b1100111 @
b1100001 C
1-
#1010000
0-
#1015000
b1100010 C
b1100110 @
1%
1-
#1020000
0-
#1025000
1%
b1100101 @
b1100011 C
1-
#1030000
0-
#1035000
b1100100 C
b1100100 @
1%
1-
#1040000
0-
#1045000
1%
b1100011 @
b1100101 C
1-
#1050000
0-
#1055000
b1100110 C
b1100010 @
1%
1-
#1060000
0-
#1065000
1%
b1100001 @
b1100111 C
1-
#1070000
0-
#1075000
b1101000 C
b1100000 @
1%
1-
#1080000
0-
#1085000
1%
b1011111 @
b1101001 C
1-
#1090000
0-
#1095000
b1101010 C
b1011110 @
1%
1-
#1100000
0-
#1105000
1%
b1011101 @
b1101011 C
1-
#1110000
0-
#1115000
b1101100 C
b1011100 @
1%
1-
#1120000
0-
#1125000
1%
b1011011 @
b1101101 C
1-
#1130000
0-
#1135000
b1101110 C
b1011010 @
1%
1-
#1140000
0-
#1145000
1%
b1011001 @
b1101111 C
1-
#1150000
0-
#1155000
b1110000 C
b1011000 @
1%
1-
#1160000
0-
#1165000
1%
b1010111 @
b1110001 C
1-
#1170000
0-
#1175000
b1110010 C
b1010110 @
1%
1-
#1180000
0-
#1185000
1%
b1010101 @
b1110011 C
1-
#1190000
0-
#1195000
b1110100 C
b1010100 @
1%
1-
#1200000
0-
#1205000
1%
b1010011 @
b1110101 C
1-
#1210000
0-
#1215000
b1110110 C
b1010010 @
1%
1-
#1220000
0-
#1225000
1%
b1010001 @
b1110111 C
1-
#1230000
0-
#1235000
b1111000 C
b1010000 @
1%
1-
#1240000
0-
#1245000
1%
b1001111 @
b1111001 C
1-
#1250000
0-
#1255000
b1111010 C
b1001110 @
1%
1-
#1260000
0-
#1265000
1%
b1001101 @
b1111011 C
1-
#1270000
0-
#1275000
b1111100 C
b1001100 @
1%
1-
#1280000
0-
#1285000
1%
b1001011 @
b1111101 C
1-
#1290000
0-
#1295000
b1111110 C
b1001010 @
1%
1-
#1300000
0-
#1305000
1%
b1001001 @
b1111111 C
1-
#1310000
0-
#1315000
b10000000 C
b1001000 @
1%
1-
#1320000
0-
#1325000
1%
b1000111 @
b10000001 C
1-
#1330000
0-
#1335000
b10000010 C
b1000110 @
1%
1-
#1340000
0-
#1345000
1%
b1000101 @
b10000011 C
1-
#1350000
0-
#1355000
b10000100 C
b1000100 @
1%
1-
#1360000
0-
#1365000
1%
b1000011 @
b10000101 C
1-
#1370000
0-
#1375000
b10000110 C
b1000010 @
1%
1-
#1380000
0-
#1385000
1%
b1000001 @
b10000111 C
1-
#1390000
0-
#1395000
b10001000 C
b1000000 @
1%
1-
#1400000
0-
#1405000
1%
b111111 @
b10001001 C
1-
#1410000
0-
#1415000
b10001010 C
b111110 @
1%
1-
#1420000
0-
#1425000
1%
b111101 @
b10001011 C
1-
#1430000
0-
#1435000
b10001100 C
b111100 @
1%
1-
#1440000
0-
#1445000
1%
b111011 @
b10001101 C
1-
#1450000
0-
#1455000
b10001110 C
b111010 @
1%
1-
#1460000
0-
#1465000
1%
b111001 @
b10001111 C
1-
#1470000
0-
#1475000
b10010000 C
b111000 @
1%
1-
#1480000
0-
#1485000
1%
b110111 @
b10010001 C
1-
#1490000
0-
#1495000
b10010010 C
b110110 @
1%
1-
#1500000
0-
#1505000
1%
b110101 @
b10010011 C
1-
#1510000
0-
#1515000
b10010100 C
b110100 @
1%
1-
#1520000
0-
#1525000
1%
b110011 @
b10010101 C
1-
#1530000
0-
#1535000
b10010110 C
b110010 @
1%
1-
#1540000
0-
#1545000
1%
b110001 @
b10010111 C
1-
#1550000
0-
#1555000
b10011000 C
b110000 @
1%
1-
#1560000
0-
#1565000
1%
b101111 @
b10011001 C
1-
#1570000
0-
#1575000
b10011010 C
b101110 @
1%
1-
#1580000
0-
#1585000
1%
b101101 @
b10011011 C
1-
#1590000
0-
#1595000
b10011100 C
b101100 @
1%
1-
#1600000
0-
#1605000
1%
b101011 @
b10011101 C
1-
#1610000
0-
#1615000
b10011110 C
b101010 @
1%
1-
#1620000
0-
#1625000
1%
b101001 @
b10011111 C
1-
#1630000
0-
#1635000
b10100000 C
b101000 @
1%
1-
#1640000
0-
#1645000
1%
b100111 @
b10100001 C
1-
#1650000
0-
#1655000
b10100010 C
b100110 @
1%
1-
#1660000
0-
#1665000
1%
b100101 @
b10100011 C
1-
#1670000
0-
#1675000
b10100100 C
b100100 @
1%
1-
#1680000
0-
#1685000
1%
b100011 @
b10100101 C
1-
#1690000
0-
#1695000
b10100110 C
b100010 @
1%
1-
#1700000
0-
#1705000
1%
b100001 @
b10100111 C
1-
#1710000
0-
#1715000
b10101000 C
b100000 @
1%
1-
#1720000
0-
#1725000
1%
b11111 @
b10101001 C
1-
#1730000
0-
#1735000
b10101010 C
b11110 @
1%
1-
#1740000
0-
#1745000
1%
b11101 @
b10101011 C
1-
#1750000
0-
#1755000
b10101100 C
b11100 @
1%
1-
#1760000
0-
#1765000
1%
b11011 @
b10101101 C
1-
#1770000
0-
#1775000
b10101110 C
b11010 @
1%
1-
#1780000
0-
#1785000
1%
b11001 @
b10101111 C
1-
#1790000
0-
#1795000
b10110000 C
b11000 @
1%
1-
#1800000
0-
#1805000
1%
b10111 @
b10110001 C
1-
#1810000
0-
#1815000
b10110010 C
b10110 @
1%
1-
#1820000
0-
#1825000
1%
b10101 @
b10110011 C
1-
#1830000
0-
#1835000
b10110100 C
b10100 @
1%
1-
#1840000
0-
#1845000
1%
b10011 @
b10110101 C
1-
#1850000
0-
#1855000
b10110110 C
b10010 @
1%
1-
#1860000
0-
#1865000
1%
b10001 @
b10110111 C
1-
#1870000
0-
#1875000
b10111000 C
b10000 @
1%
1-
#1880000
0-
#1885000
1%
b1111 @
b10111001 C
1-
#1890000
0-
#1895000
b10111010 C
b1110 @
1%
1-
#1900000
0-
#1905000
1%
b1101 @
b10111011 C
1-
#1910000
0-
#1915000
b10111100 C
b1100 @
1%
1-
#1920000
0-
#1925000
1%
b1011 @
b10111101 C
1-
#1930000
0-
#1935000
b10111110 C
b1010 @
1%
1-
#1940000
0-
#1945000
1%
b1001 @
b10111111 C
1-
#1950000
0-
#1955000
b11000000 C
b1000 @
1%
1-
#1960000
0-
#1965000
1%
b111 @
b11000001 C
1-
#1970000
0-
#1975000
b11000010 C
b110 @
1%
1-
#1980000
0-
#1985000
1%
b101 @
b11000011 C
1-
#1990000
0-
#1995000
b11000100 C
b100 @
1%
1-
#2000000
0-
#2005000
1%
b11 @
b11000101 C
1-
#2010000
0-
#2015000
b11000110 C
b10 @
1%
1-
#2020000
0-
#2025000
1%
b1 @
b11000111 C
1-
#2030000
0-
#2035000
b11001000 C
b0 @
1%
1-
#2040000
0-
#2045000
b10 <
b10000000000 )
b10000000000 D
0"
0#
b1 G
0%
b11001001 C
1-
#2050000
0-
#2055000
b11001010 C
b1 <
1"
1#
1-
#2060000
0-
#2065000
b0 <
b11001011 C
1-
#2070000
0-
#2075000
b11001100 C
b1001 <
0'
0#
b10 G
1-
#2080000
0-
#2085000
1'
1#
b1000 <
b11001101 C
1-
#2090000
0-
#2095000
b11001110 C
b111 <
1-
#2100000
0-
#2105000
b110 <
b11001111 C
1-
#2110000
0-
#2115000
b11010000 C
b101 <
1-
#2120000
0-
#2125000
b100 <
b11010001 C
1-
#2130000
0-
#2135000
b11010010 C
b11 <
1-
#2140000
0-
#2145000
b10 <
b11010011 C
1-
#2150000
0-
#2155000
b11010100 C
b1 <
1-
#2160000
0-
#2165000
b0 <
b11010101 C
1-
#2170000
0-
#2175000
b11010110 C
b1001 <
0'
0#
b11 G
1-
#2180000
0-
#2185000
1'
1#
b1000 <
b11010111 C
1-
#2190000
0-
#2195000
b11011000 C
b111 <
1-
#2200000
0-
#2205000
b110 <
b11011001 C
1-
#2210000
0-
#2215000
b11011010 C
b101 <
1-
#2220000
0-
#2225000
b100 <
b11011011 C
1-
#2230000
0-
#2235000
b11011100 C
b11 <
1-
#2240000
0-
#2245000
b10 <
b11011101 C
1-
#2250000
0-
#2255000
b11011110 C
b1 <
1-
#2260000
0-
#2265000
b0 <
b11011111 C
1-
#2270000
0-
#2275000
b11100000 C
b10 <
b100000 )
b100000 D
0"
0'
0#
b100 G
1-
#2280000
0-
#2285000
1"
1'
1#
b1 <
b11100001 C
1-
#2290000
0-
#2295000
b11100010 C
b0 <
1-
#2300000
0-
#2305000
b101 G
b11100011 C
1-
#2310000
0-
#2315000
b11100100 C
b10 <
b0 )
b0 D
0#
b111 G
1,
1J
b11 H
b1010101111001101 I
b100000000 :
10
12
b1010101111001101 1
b1010101111001101 7
b100000000 .
b100000000 5
1-
#2320000
0-
#2325000
0,
1#
b1 <
b11100101 C
00
1-
#2330000
0-
#2335000
b11100110 C
b0 <
1-
#2340000
0-
#2345000
b1010101111001101 !
b1010101111001101 8
b100 <
b0 $
b0 F
b1010101111001101 >
1=
b1100000000 )
b1100000000 D
0"
0'
b1001 G
b11100111 C
1-
#2350000
0-
#2355000
b11101000 C
b11 <
1=
1"
1'
1-
#2360000
0-
#2365000
1=
b10 <
b11101001 C
1-
#2370000
0-
#2375000
b11101010 C
b1 <
1=
1-
#2380000
0-
#2385000
1=
b0 <
b11101011 C
1-
#2390000
0-
#2395000
bz !
bz 8
b11101100 C
b101 G
0=
1-
#2400000
0-
